cspb_tools/__init__.py
cspb_tools/cspb_gui.glade
cspb_tools/cspb_gui.py
cspb_tools/run_cspb_gui.py
cspb_tools-1.0.1.dist-info/LICENSE
cspb_tools-1.0.1.dist-info/METADATA
cspb_tools-1.0.1.dist-info/WHEEL
cspb_tools-1.0.1.dist-info/entry_points.txt
cspb_tools-1.0.1.dist-info/top_level.txt
cspb_tools-1.0.1.dist-info/RECORD
